{
 "cells": [
  {
   "cell_type": "code",
   "execution_count": 7,
   "metadata": {},
   "outputs": [],
   "source": [
    "from dis import dis"
   ]
  },
  {
   "cell_type": "code",
   "execution_count": 3,
   "metadata": {},
   "outputs": [
    {
     "data": {
      "text/plain": [
       "[1, 2, 3]"
      ]
     },
     "execution_count": 3,
     "metadata": {},
     "output_type": "execute_result"
    }
   ],
   "source": [
    "[1, 2, 3]"
   ]
  },
  {
   "cell_type": "code",
   "execution_count": 4,
   "metadata": {},
   "outputs": [
    {
     "data": {
      "text/plain": [
       "(1, 2, 3)"
      ]
     },
     "execution_count": 4,
     "metadata": {},
     "output_type": "execute_result"
    }
   ],
   "source": [
    "1, 2, 3"
   ]
  },
  {
   "cell_type": "code",
   "execution_count": 5,
   "metadata": {},
   "outputs": [
    {
     "data": {
      "text/plain": [
       "<code object <module> at 0x10bb2d390, file \"string\", line 1>"
      ]
     },
     "execution_count": 5,
     "metadata": {},
     "output_type": "execute_result"
    }
   ],
   "source": [
    "compile(\"(1, 2, 3, 'a')\", \"string\", \"eval\")"
   ]
  },
  {
   "cell_type": "code",
   "execution_count": 10,
   "metadata": {
    "collapsed": false
   },
   "outputs": [
    {
     "name": "stdout",
     "output_type": "stream",
     "text": [
      "  1           0 LOAD_CONST               4 ((1, 2, 3, 'a'))\n              2 RETURN_VALUE\n"
     ]
    }
   ],
   "source": [
    "dis(compile(\"(1, 2, 3, 'a')\", \"string\", \"eval\"))"
   ]
  },
  {
   "cell_type": "code",
   "execution_count": 20,
   "metadata": {},
   "outputs": [
    {
     "name": "stdout",
     "output_type": "stream",
     "text": [
      "  1           0 LOAD_CONST               0 (1)\n              2 LOAD_CONST               1 (2)\n              4 LOAD_CONST               2 (3)\n              6 LOAD_CONST               3 ('a')\n              8 BUILD_LIST               4\n             10 RETURN_VALUE\n"
     ]
    }
   ],
   "source": [
    "\n",
    "dis(compile(\"[1, 2, 3, 'a']\", \"string\", \"eval\"))"
   ]
  },
  {
   "cell_type": "code",
   "execution_count": 21,
   "metadata": {},
   "outputs": [
    {
     "name": "stdout",
     "output_type": "stream",
     "text": [
      "  1           0 LOAD_CONST               0 (1)\n              2 LOAD_CONST               1 (2)\n              4 LOAD_CONST               2 (3)\n              6 LOAD_CONST               0 (1)\n              8 LOAD_CONST               2 (3)\n             10 BUILD_LIST               2\n             12 BUILD_TUPLE              4\n             14 RETURN_VALUE\n"
     ]
    }
   ],
   "source": [
    "dis(compile(\"(1, 2, 3, [1, 3])\", \"string\", \"eval\"))"
   ]
  },
  {
   "cell_type": "code",
   "execution_count": 33,
   "metadata": {},
   "outputs": [],
   "source": [
    "from timeit import timeit"
   ]
  },
  {
   "cell_type": "code",
   "execution_count": 38,
   "metadata": {},
   "outputs": [
    {
     "data": {
      "text/plain": [
       "0.33908398397034034"
      ]
     },
     "execution_count": 38,
     "metadata": {},
     "output_type": "execute_result"
    }
   ],
   "source": [
    "timeit(\"(1, 2, 3, 4, 5)\", number=10_000_000)"
   ]
  },
  {
   "cell_type": "code",
   "execution_count": 39,
   "metadata": {},
   "outputs": [
    {
     "data": {
      "text/plain": [
       "0.9704343309858814"
      ]
     },
     "execution_count": 39,
     "metadata": {},
     "output_type": "execute_result"
    }
   ],
   "source": [
    "timeit(\"[1, 2, 3, 4, 5]\", number=10_000_000)"
   ]
  },
  {
   "cell_type": "code",
   "execution_count": 40,
   "metadata": {},
   "outputs": [],
   "source": [
    "def fn1():\n",
    "    pass"
   ]
  },
  {
   "cell_type": "code",
   "execution_count": 42,
   "metadata": {},
   "outputs": [
    {
     "name": "stdout",
     "output_type": "stream",
     "text": [
      "  1           0 LOAD_NAME                0 (fn1)\n              2 LOAD_CONST               0 (10)\n              4 LOAD_CONST               1 (20)\n              6 BUILD_TUPLE              3\n              8 RETURN_VALUE\n"
     ]
    }
   ],
   "source": [
    "dis(compile(\"(fn1, 10, 20)\", \"string\", \"eval\"))"
   ]
  },
  {
   "cell_type": "code",
   "execution_count": null,
   "metadata": {},
   "outputs": [],
   "source": []
  },
  {
   "cell_type": "code",
   "execution_count": null,
   "metadata": {},
   "outputs": [],
   "source": []
  },
  {
   "cell_type": "code",
   "execution_count": null,
   "metadata": {},
   "outputs": [],
   "source": []
  },
  {
   "cell_type": "code",
   "execution_count": null,
   "metadata": {},
   "outputs": [],
   "source": []
  },
  {
   "cell_type": "code",
   "execution_count": null,
   "metadata": {},
   "outputs": [],
   "source": []
  },
  {
   "cell_type": "code",
   "execution_count": null,
   "metadata": {},
   "outputs": [],
   "source": []
  }
 ],
 "metadata": {
  "kernelspec": {
   "display_name": "Python 2",
   "language": "python",
   "name": "python2"
  },
  "language_info": {
   "codemirror_mode": {
    "name": "ipython",
    "version": 2
   },
   "file_extension": ".py",
   "mimetype": "text/x-python",
   "name": "python",
   "nbconvert_exporter": "python",
   "pygments_lexer": "ipython2",
   "version": "2.7.6"
  }
 },
 "nbformat": 4,
 "nbformat_minor": 0
}
